MANIFEST.in
README.md
setup.cfg
setup.py
treeprinter/__init__.py
treeprinter/__meta__.py
treeprinter/utils.py
treeprinter.egg-info/PKG-INFO
treeprinter.egg-info/SOURCES.txt
treeprinter.egg-info/dependency_links.txt
treeprinter.egg-info/top_level.txt
treeprinter/printers/__init__.py
treeprinter/printers/base.py
treeprinter/printers/default_printer.py
treeprinter/printers/json_printer.py
treeprinter/tests/__init__.py
treeprinter/tests/test_base_printer.py
treeprinter/tests/test_default_printer.py
treeprinter/tests/test_utils.py