Metadata-Version: 1.1
Name: treeprinter
Version: 0.0.2
Summary: Python library for easy tree displaying
Home-page: https://github.com/percevalw/treeprinter
Author: Perceval Wajsburt
Author-email: perceval.wajsburt@gmail.com
License: MIT License
Platform: UNKNOWN
Classifier: Development Status :: 5 - Production/Stable
Classifier: Intended Audience :: Developers
Classifier: License :: OSI Approved :: BSD License
Classifier: Programming Language :: C
Classifier: Programming Language :: Python :: 2.4
Classifier: Programming Language :: Python :: 2.5
Classifier: Programming Language :: Python :: 2.6
Classifier: Programming Language :: Python :: 2.7
Classifier: Programming Language :: Python :: 3
Classifier: Programming Language :: Python :: 3.2
